ovos_padatious/__init__.py
ovos_padatious/__main__.py
ovos_padatious/bracket_expansion.py
ovos_padatious/domain_container.py
ovos_padatious/entity.py
ovos_padatious/entity_edge.py
ovos_padatious/entity_manager.py
ovos_padatious/id_manager.py
ovos_padatious/intent.py
ovos_padatious/intent_container.py
ovos_padatious/intent_manager.py
ovos_padatious/match_data.py
ovos_padatious/opm.py
ovos_padatious/padaos.py
ovos_padatious/pos_intent.py
ovos_padatious/simple_intent.py
ovos_padatious/train_data.py
ovos_padatious/trainable.py
ovos_padatious/training_manager.py
ovos_padatious/util.py
ovos_padatious/version.py
ovos_padatious-1.4.3.dist-info/licenses/LICENSE
ovos_padatious-1.4.3.dist-info/METADATA
ovos_padatious-1.4.3.dist-info/WHEEL
ovos_padatious-1.4.3.dist-info/entry_points.txt
ovos_padatious-1.4.3.dist-info/top_level.txt
ovos_padatious-1.4.3.dist-info/zip-safe
ovos_padatious-1.4.3.dist-info/RECORD
