Metadata-Version: 2.4
Name: ovos_padatious
Version: 1.4.3
Summary: A neural network intent parser
Home-page: https://github.com/OpenVoiceOS/ovos-padatious-pipeline-plugin
Author: Matthew Scholefield
License: Apache-2.0
Keywords: intent-parser parser text text-processing
Classifier: Development Status :: 3 - Alpha
Classifier: Intended Audience :: Developers
Classifier: Topic :: Text Processing :: Linguistic
Classifier: License :: OSI Approved :: Apache Software License
Classifier: Programming Language :: Python :: 2
Classifier: Programming Language :: Python :: 2.7
Classifier: Programming Language :: Python :: 3
Classifier: Programming Language :: Python :: 3.0
Classifier: Programming Language :: Python :: 3.1
Classifier: Programming Language :: Python :: 3.2
Classifier: Programming Language :: Python :: 3.3
Classifier: Programming Language :: Python :: 3.4
Classifier: Programming Language :: Python :: 3.5
Classifier: Programming Language :: Python :: 3.6
Classifier: Programming Language :: Python :: 3.7
Classifier: Programming Language :: Python :: 3.8
License-File: LICENSE
Requires-Dist: fann2<1.1.0,>=1.0.7
Requires-Dist: xxhash
Requires-Dist: ovos-plugin-manager<3.0.0,>=0.5.0
Requires-Dist: ovos-workshop<8.0.0,>=0.1.7
Requires-Dist: ovos-utils<1.0.0,>=0.7.0
Requires-Dist: langcodes
Requires-Dist: snowballstemmer
Requires-Dist: PyStemmer
Dynamic: author
Dynamic: classifier
Dynamic: description
Dynamic: description-content-type
Dynamic: home-page
Dynamic: keywords
Dynamic: license
Dynamic: license-file
Dynamic: requires-dist
Dynamic: summary
